setup.py
tm1640.py
micropython_tm1640.egg-info/PKG-INFO
micropython_tm1640.egg-info/SOURCES.txt
micropython_tm1640.egg-info/dependency_links.txt
micropython_tm1640.egg-info/top_level.txt