Metadata-Version: 1.1
Name: micropython-tm1640
Version: 1.0.0
Summary: MicroPython library for TM1640 LED driver.
Home-page: https://github.com/mcauser/micropython-tm1640
Author: Mike Causer
Author-email: mcauser@gmail.com
License: MIT
Keywords: tm1640 led matrix micropython
Platform: UNKNOWN
Classifier: Development Status :: 5 - Production/Stable
Classifier: Programming Language :: Python :: Implementation :: MicroPython
Classifier: License :: OSI Approved :: MIT License
